{
  "project_info": {
    "project_number": "407409687631",
    "project_id": "agendauto",
    "storage_bucket": "agendauto.appspot.com"
  },
  "client": [
    {
      "client_info": {
        "mobilesdk_app_id": "1:407409687631:android:34d44256003ed99f61fe3a",
        "android_client_info": {
          "package_name": "silva.robson.william.projetodma"
        }
      },
      "oauth_client": [],
      "api_key": [
        {
          "current_key": "AIzaSyAl8gNiA7ask90RgQA6KHVuY1w_k0ZDAPE"
        }
      ],
      "services": {
        "appinvite_service": {
          "other_platform_oauth_client": []
        }
      }
    }
  ],
  "configuration_version": "1"
}